odoo/addons/queue_job/README.rst
odoo/addons/queue_job/__init__.py
odoo/addons/queue_job/__manifest__.py
odoo/addons/queue_job/delay.py
odoo/addons/queue_job/exception.py
odoo/addons/queue_job/fields.py
odoo/addons/queue_job/job.py
odoo/addons/queue_job/controllers/__init__.py
odoo/addons/queue_job/controllers/main.py
odoo/addons/queue_job/data/queue_data.xml
odoo/addons/queue_job/data/queue_job_function_data.xml
odoo/addons/queue_job/hooks/post_init_hook.py
odoo/addons/queue_job/i18n/da.po
odoo/addons/queue_job/i18n/de.po
odoo/addons/queue_job/i18n/es.po
odoo/addons/queue_job/i18n/fr.po
odoo/addons/queue_job/i18n/pt.po
odoo/addons/queue_job/i18n/queue_job.pot
odoo/addons/queue_job/i18n/zh_CN.po
odoo/addons/queue_job/jobrunner/__init__.py
odoo/addons/queue_job/jobrunner/channels.py
odoo/addons/queue_job/jobrunner/runner.py
odoo/addons/queue_job/migrations/12.0.1.0.1/post-migration.py
odoo/addons/queue_job/migrations/12.0.1.0.1/pre-migration.py
odoo/addons/queue_job/migrations/12.0.2.0.0/post-migration.py
odoo/addons/queue_job/migrations/12.0.2.1.0/pre-migration.py
odoo/addons/queue_job/migrations/12.0.2.2.0/pre-migration.py
odoo/addons/queue_job/migrations/12.0.2.3.0/post-migration.py
odoo/addons/queue_job/models/__init__.py
odoo/addons/queue_job/models/base.py
odoo/addons/queue_job/models/ir_model_fields.py
odoo/addons/queue_job/models/queue_job.py
odoo/addons/queue_job/readme/CONFIGURE.rst
odoo/addons/queue_job/readme/CONTRIBUTORS.rst
odoo/addons/queue_job/readme/DESCRIPTION.rst
odoo/addons/queue_job/readme/HISTORY.rst
odoo/addons/queue_job/readme/INSTALL.rst
odoo/addons/queue_job/readme/ROADMAP.rst
odoo/addons/queue_job/readme/USAGE.rst
odoo/addons/queue_job/security/ir.model.access.csv
odoo/addons/queue_job/security/security.xml
odoo/addons/queue_job/static/description/icon.png
odoo/addons/queue_job/static/description/icon.svg
odoo/addons/queue_job/static/description/index.html
odoo/addons/queue_job/static/lib/vis/vis-network.min.css
odoo12_addon_queue_job-12.0.4.1.0.dist-info/METADATA
odoo12_addon_queue_job-12.0.4.1.0.dist-info/WHEEL
odoo12_addon_queue_job-12.0.4.1.0.dist-info/top_level.txt
odoo12_addon_queue_job-12.0.4.1.0.dist-info/RECORD
